show_puntigam/__init__.py
show_puntigam-0.0.3.dist-info/DESCRIPTION.rst
show_puntigam-0.0.3.dist-info/METADATA
show_puntigam-0.0.3.dist-info/RECORD
show_puntigam-0.0.3.dist-info/WHEEL
show_puntigam-0.0.3.dist-info/metadata.json
show_puntigam-0.0.3.dist-info/top_level.txt
