Metadata-Version: 2.0
Name: show-puntigam
Version: 0.0.3
Summary: Python package to evaluate urban lidar datasets.
Home-page: https://gitlab.v2c2.at/michaelhartmann/show_puntigam
Author-email: michael.hartmann@v2c2.at
License: UNKNOWN
Download-URL: https://gitlab.v2c2.at/michaelhartmann/show_puntigam
Platform: UNKNOWN
